<annotation>
	<folder>train</folder>
	<filename>apple_54.jpg</filename>
	<path>C:\tensorflow1\models\research\object_detection\images\train\apple_54.jpg</path>
	<source>
		<database>Unknown</database>
	</source>
	<size>
		<width>1023</width>
		<height>936</height>
		<depth>3</depth>
	</size>
	<segmented>0</segmented>
	<object>
		<name>apple</name>
		<pose>Unspecified</pose>
		<truncated>0</truncated>
		<difficult>0</difficult>
		<bndbox>
			<xmin>87</xmin>
			<ymin>265</ymin>
			<xmax>694</xmax>
			<ymax>868</ymax>
		</bndbox>
	</object>
</annotation>
